pallet_patcher/__init__.py
pallet_patcher/__main__.py
pallet_patcher/command.py
pallet_patcher/manifest.py
pallet_patcher/search.py
pallet_patcher-0.0.1.dist-info/LICENSE
pallet_patcher-0.0.1.dist-info/METADATA
pallet_patcher-0.0.1.dist-info/WHEEL
pallet_patcher-0.0.1.dist-info/entry_points.txt
pallet_patcher-0.0.1.dist-info/top_level.txt
pallet_patcher-0.0.1.dist-info/zip-safe
pallet_patcher-0.0.1.dist-info/RECORD
